MANIFEST.in
README.rst
requirements.txt
setup.py
chrome_edit_server_gmail_filter/__init__.py
chrome_edit_server_gmail_filter/filter.py
chrome_edit_server_gmail_filter.egg-info/PKG-INFO
chrome_edit_server_gmail_filter.egg-info/SOURCES.txt
chrome_edit_server_gmail_filter.egg-info/dependency_links.txt
chrome_edit_server_gmail_filter.egg-info/entry_points.txt
chrome_edit_server_gmail_filter.egg-info/requires.txt
chrome_edit_server_gmail_filter.egg-info/top_level.txt