Metadata-Version: 1.1
Name: chrome-edit-server-gmail-filter
Version: 0.3.1
Summary: A chrome-edit-server plugin allowing one to edit Gmail messages
Home-page: https://github.com/coddingtonbear/chrome-edit-server-gmail-filter
Author: Tim Cuthbertson
Author-email: tim@gfxmonk.net
License: UNKNOWN
Platform: UNKNOWN
Classifier: Operating System :: OS Independent
